Workbook

Sheet Raw_Data
A1: Order_ID | B1: Order_Date | C1: State | D1: Region | E1: Product | F1: Category | G1: Quantity | H1: Unit_Price | I1: Discount | J1: Revenue
A2: 1 | B2: 45678 | C2: Rajasthan | D2: North | E2: Keyboard | F2: Accessories | G2: 5 | H2: 1920.83 | I2: 0 | J2: 9604.13
A3: 2 | B3: 45757 | C3: Rajasthan | D3: North | E3: Monitor | F3: Computing | G3: 3 | H3: 17823.96 | I3: 0 | J3: 53471.87
A4: 3 | B4: 45951 | C4: Uttar Pradesh | D4: North | E4: Printer | F4: Office | G4: 6 | H4: 12639.36 | I4: 0 | J4: 75836.14
A5: 4 | B5: 45910 | C5: West Bengal | D5: East | E5: Keyboard | F5: Accessories | G5: 5 | H5: 1848.23 | I5: 0.05 | J5: 8779.11
A6: 5 | B6: 45845 | C6: Karnataka | D6: South | E6: Laptop | F6: Computing | G6: 1 | H6: 63437.83 | I6: 0.05 | J6: 60265.94
A7: 6 | B7: 45712 | C7: Andhra Pradesh | D7: South | E7: Software | F7: Software | G7: 6 | H7: 6959.41 | I7: 0.08 | J7: 38415.96
A8: 7 | B8: 45986 | C8: Delhi | D8: North | E8: Laptop | F8: Computing | G8: 3 | H8: 67812.8 | I8: 0.08 | J8: 187163.32
A9: 8 | B9: 45922 | C9: Rajasthan | D9: North | E9: Monitor | F9: Computing | G9: 4 | H9: 18273.41 | I9: 0.1 | J9: 65784.26
A10: 9 | B10: 45921 | C10: Gujarat | D10: West | E10: Mouse | F10: Accessories | G10: 2 | H10: 887.07 | I10: 0.05 | J10: 1685.44
A11: 10 | B11: 45659 | C11: Telangana | D11: South | E11: Printer | F11: Office | G11: 6 | H11: 11084.84 | I11: 0.03 | J11: 64513.77
A12: 11 | B12: 45848 | C12: Kerala | D12: South | E12: Software | F12: Software | G12: 6 | H12: 6932.74 | I12: 0.05 | J12: 39516.61
A13: 12 | B13: 45927 | C13: West Bengal | D13: East | E13: Monitor | F13: Computing | G13: 4 | H13: 19705.65 | I13: 0.1 | J13: 70940.35
... A401: 400 | B401: 45664 | C401: West Bengal | D401: East | E401: Mouse | F401: Accessories | G401: 4 | H401: 933.28 | I401: 0.05 | J401: 3546.47

Sheet Lookup
A1: State | B1: Region | C1: Manager
A2: Bihar | B2: East | C2: Amit
A3: West Bengal | B3: East | C3: Neha
A4: Odisha | B4: East | C4: Ravi
A5: Delhi | B5: North | C5: Priya
A6: Punjab | B6: North | C6: Sanjay
A7: Haryana | B7: North | C7: Anita
A8: Rajasthan | B8: North | C8: Amit
A9: Uttar Pradesh | B9: North | C9: Neha
A10: Maharashtra | B10: West | C10: Ravi
A11: Gujarat | B11: West | C11: Priya
A12: Goa | B12: West | C12: Sanjay
... A17: Andhra Pradesh | B17: South | C17: Priya

Sheet Analysis
A1: Advanced Excel Sales Analysis
A3: State | B3: Revenue | C3: Quantity | D3: Region (VLOOKUP) | E3: Manager (INDEX-MATCH)
A4: Bihar | B4: =SUMIF(Raw_Data!$C:$C,A4,Raw_Data!$J:$J) -> 2272636.4 | C4: =SUMIF(Raw_Data!$C:$C,A4,Raw_Data!$G:$G) -> 118 | D4: =VLOOKUP(A4,Lookup!$A:$C,2,FALSE) -> East | E4: =INDEX(Lookup!$C:$C,MATCH(A4,Lookup!$A:$A,0)) -> Amit
A5: West Bengal | B5: =SUMIF(Raw_Data!$C:$C,A5,Raw_Data!$J:$J) -> 1428648.9 | C5: =SUMIF(Raw_Data!$C:$C,A5,Raw_Data!$G:$G) -> 70 | D5: =VLOOKUP(A5,Lookup!$A:$C,2,FALSE) -> East | E5: =INDEX(Lookup!$C:$C,MATCH(A5,Lookup!$A:$A,0)) -> Neha
A6: Odisha | B6: =SUMIF(Raw_Data!$C:$C,A6,Raw_Data!$J:$J) -> 1446192.3 | C6: =SUMIF(Raw_Data!$C:$C,A6,Raw_Data!$G:$G) -> 121 | D6: =VLOOKUP(A6,Lookup!$A:$C,2,FALSE) -> East | E6: =INDEX(Lookup!$C:$C,MATCH(A6,Lookup!$A:$A,0)) -> Ravi
A7: Delhi | B7: =SUMIF(Raw_Data!$C:$C,A7,Raw_Data!$J:$J) -> 2550155.8 | C7: =SUMIF(Raw_Data!$C:$C,A7,Raw_Data!$G:$G) -> 111 | D7: =VLOOKUP(A7,Lookup!$A:$C,2,FALSE) -> North | E7: =INDEX(Lookup!$C:$C,MATCH(A7,Lookup!$A:$A,0)) -> Priya
A8: Punjab | B8: =SUMIF(Raw_Data!$C:$C,A8,Raw_Data!$J:$J) -> 1504764.3 | C8: =SUMIF(Raw_Data!$C:$C,A8,Raw_Data!$G:$G) -> 63 | D8: =VLOOKUP(A8,Lookup!$A:$C,2,FALSE) -> North | E8: =INDEX(Lookup!$C:$C,MATCH(A8,Lookup!$A:$A,0)) -> Sanjay
A9: Haryana | B9: =SUMIF(Raw_Data!$C:$C,A9,Raw_Data!$J:$J) -> 1860235.1 | C9: =SUMIF(Raw_Data!$C:$C,A9,Raw_Data!$G:$G) -> 84 | D9: =VLOOKUP(A9,Lookup!$A:$C,2,FALSE) -> North | E9: =INDEX(Lookup!$C:$C,MATCH(A9,Lookup!$A:$A,0)) -> Anita
A10: Rajasthan | B10: =SUMIF(Raw_Data!$C:$C,A10,Raw_Data!$J:$J) -> 2359918.2 | C10: =SUMIF(Raw_Data!$C:$C,A10,Raw_Data!$G:$G) -> 164 | D10: =VLOOKUP(A10,Lookup!$A:$C,2,FALSE) -> North | E10: =INDEX(Lookup!$C:$C,MATCH(A10,Lookup!$A:$A,0)) -> Amit
A11: Uttar Pradesh | B11: =SUMIF(Raw_Data!$C:$C,A11,Raw_Data!$J:$J) -> 2060248.6 | C11: =SUMIF(Raw_Data!$C:$C,A11,Raw_Data!$G:$G) -> 117 | D11: =VLOOKUP(A11,Lookup!$A:$C,2,FALSE) -> North | E11: =INDEX(Lookup!$C:$C,MATCH(A11,Lookup!$A:$A,0)) -> Neha
A12: Maharashtra | B12: =SUMIF(Raw_Data!$C:$C,A12,Raw_Data!$J:$J) -> 2841717.5 | C12: =SUMIF(Raw_Data!$C:$C,A12,Raw_Data!$G:$G) -> 131 | D12: =VLOOKUP(A12,Lookup!$A:$C,2,FALSE) -> West | E12: =INDEX(Lookup!$C:$C,MATCH(A12,Lookup!$A:$A,0)) -> Ravi
A13: Gujarat | B13: =SUMIF(Raw_Data!$C:$C,A13,Raw_Data!$J:$J) -> 2758932.3 | C13: =SUMIF(Raw_Data!$C:$C,A13,Raw_Data!$G:$G) -> 153 | D13: =VLOOKUP(A13,Lookup!$A:$C,2,FALSE) -> West | E13: =INDEX(Lookup!$C:$C,MATCH(A13,Lookup!$A:$A,0)) -> Priya
A14: Goa | B14: =SUMIF(Raw_Data!$C:$C,A14,Raw_Data!$J:$J) -> 1393088.2 | C14: =SUMIF(Raw_Data!$C:$C,A14,Raw_Data!$G:$G) -> 93 | D14: =VLOOKUP(A14,Lookup!$A:$C,2,FALSE) -> West | E14: =INDEX(Lookup!$C:$C,MATCH(A14,Lookup!$A:$A,0)) -> Sanjay
A15: Karnataka | B15: =SUMIF(Raw_Data!$C:$C,A15,Raw_Data!$J:$J) -> 1312458.4 | C15: =SUMIF(Raw_Data!$C:$C,A15,Raw_Data!$G:$G) -> 107 | D15: =VLOOKUP(A15,Lookup!$A:$C,2,FALSE) -> South | E15: =INDEX(Lookup!$C:$C,MATCH(A15,Lookup!$A:$A,0)) -> Anita
... A19: Andhra Pradesh | B19: =SUMIF(Raw_Data!$C:$C,A19,Raw_Data!$J:$J) -> 1788427.2 | C19: =SUMIF(Raw_Data!$C:$C,A19,Raw_Data!$G:$G) -> 101 | D19: =VLOOKUP(A19,Lookup!$A:$C,2,FALSE) -> South | E19: =INDEX(Lookup!$C:$C,MATCH(A19,Lookup!$A:$A,0)) -> Priya
A22: Product | B22: Revenue | C22: Quantity
A23: Laptop | B23: =SUMIF(Raw_Data!$E:$E,A23,Raw_Data!$J:$J) -> 19278404 | C23: =SUMIF(Raw_Data!$E:$E,A23,Raw_Data!$G:$G) -> 310
A24: Monitor | B24: =SUMIF(Raw_Data!$E:$E,A24,Raw_Data!$J:$J) -> 5909901.2 | C24: =SUMIF(Raw_Data!$E:$E,A24,Raw_Data!$G:$G) -> 344
A25: Printer | B25: =SUMIF(Raw_Data!$E:$E,A25,Raw_Data!$J:$J) -> 3405102.2 | C25: =SUMIF(Raw_Data!$E:$E,A25,Raw_Data!$G:$G) -> 295
A26: Keyboard | B26: =SUMIF(Raw_Data!$E:$E,A26,Raw_Data!$J:$J) -> 553330.28 | C26: =SUMIF(Raw_Data!$E:$E,A26,Raw_Data!$G:$G) -> 320
A27: Mouse | B27: =SUMIF(Raw_Data!$E:$E,A27,Raw_Data!$J:$J) -> 183431.45 | C27: =SUMIF(Raw_Data!$E:$E,A27,Raw_Data!$G:$G) -> 214
A28: Software | B28: =SUMIF(Raw_Data!$E:$E,A28,Raw_Data!$J:$J) -> 2070782.2 | C28: =SUMIF(Raw_Data!$E:$E,A28,Raw_Data!$G:$G) -> 283

Sheet Dashboard
B2: ADVANCED EXCEL SALES DASHBOARD
B5: Total Revenue | D5: Total Quantity | F5: Orders | H5: Avg Order Value
B6: =SUM(Raw_Data!J:J) -> 31400951 | D6: =SUM(Raw_Data!G:G) -> 1766 | F6: =COUNTA(Raw_Data!A:A)-1 -> 400 | H6: =AVERAGE(Raw_Data!J:J) -> 78502.377
B27: Month | C27: Revenue
B28: Jan | C28: =SUMIFS(Raw_Data!$J:$J,Raw_Data!$B:$B,">="&DATE(2025,1,1),Raw_Data!$B:$B,"<"&EDATE(DATE(2025,1,1),1)) -> 2416363.4
B29: Feb | C29: =SUMIFS(Raw_Data!$J:$J,Raw_Data!$B:$B,">="&DATE(2025,2,1),Raw_Data!$B:$B,"<"&EDATE(DATE(2025,2,1),1)) -> 2594511.8
B30: Mar | C30: =SUMIFS(Raw_Data!$J:$J,Raw_Data!$B:$B,">="&DATE(2025,3,1),Raw_Data!$B:$B,"<"&EDATE(DATE(2025,3,1),1)) -> 3040190.1
B31: Apr | C31: =SUMIFS(Raw_Data!$J:$J,Raw_Data!$B:$B,">="&DATE(2025,4,1),Raw_Data!$B:$B,"<"&EDATE(DATE(2025,4,1),1)) -> 3522156.7
B32: May | C32: =SUMIFS(Raw_Data!$J:$J,Raw_Data!$B:$B,">="&DATE(2025,5,1),Raw_Data!$B:$B,"<"&EDATE(DATE(2025,5,1),1)) -> 1721383.2
B33: Jun | C33: =SUMIFS(Raw_Data!$J:$J,Raw_Data!$B:$B,">="&DATE(2025,6,1),Raw_Data!$B:$B,"<"&EDATE(DATE(2025,6,1),1)) -> 2391905.1
B34: Jul | C34: =SUMIFS(Raw_Data!$J:$J,Raw_Data!$B:$B,">="&DATE(2025,7,1),Raw_Data!$B:$B,"<"&EDATE(DATE(2025,7,1),1)) -> 2026784.6
B35: Aug | C35: =SUMIFS(Raw_Data!$J:$J,Raw_Data!$B:$B,">="&DATE(2025,8,1),Raw_Data!$B:$B,"<"&EDATE(DATE(2025,8,1),1)) -> 4094533.2
B36: Sep | C36: =SUMIFS(Raw_Data!$J:$J,Raw_Data!$B:$B,">="&DATE(2025,9,1),Raw_Data!$B:$B,"<"&EDATE(DATE(2025,9,1),1)) -> 1223899.2
B37: Oct | C37: =SUMIFS(Raw_Data!$J:$J,Raw_Data!$B:$B,">="&DATE(2025,10,1),Raw_Data!$B:$B,"<"&EDATE(DATE(2025,10,1),1)) -> 3013759.2
B38: Nov | C38: =SUMIFS(Raw_Data!$J:$J,Raw_Data!$B:$B,">="&DATE(2025,11,1),Raw_Data!$B:$B,"<"&EDATE(DATE(2025,11,1),1)) -> 2009199.8
B39: Dec | C39: =SUMIFS(Raw_Data!$J:$J,Raw_Data!$B:$B,">="&DATE(2025,12,1),Raw_Data!$B:$B,"<"&EDATE(DATE(2025,12,1),1)) -> 3346264.8
